pvoutput_publisher/__init__.py
pvoutput_publisher/publisher.py
pvoutput_publisher/base/__init__.py
pvoutput_publisher/base/service.py
pvoutput_publisher/services/__init__.py
pvoutput_publisher/services/add_batch_status.py
pvoutput_publisher/services/add_status.py
pvoutput_publisher/services/rate_limits.py
pvoutput_publisher/services/common/__init__.py
pvoutput_publisher/services/common/group_builder.py
pvoutput_publisher-0.20.1.dist-info/METADATA
pvoutput_publisher-0.20.1.dist-info/WHEEL
pvoutput_publisher-0.20.1.dist-info/top_level.txt
pvoutput_publisher-0.20.1.dist-info/RECORD
